usbjiance/__init__.py
usbjiance/usbjiance.py
usbjiance-1.9.dist-info/METADATA
usbjiance-1.9.dist-info/WHEEL
usbjiance-1.9.dist-info/top_level.txt
usbjiance-1.9.dist-info/RECORD
